[
  {
    "num": 188,
    "date": "2026-11-28",
    "title": "浏览记录",
    "direction": "如果把你的浏览记录公开展览，你敢去吗？"
  },
  {
    "num": 189,
    "date": "2026-11-29",
    "title": "自动播放",
    "direction": "自动播放偷走了你的选择权——你以为你在看，其实是被看"
  },
  {
    "num": 190,
    "date": "2026-11-30",
    "title": "虚拟身份",
    "direction": "网上的你比真实的你更勇敢，还是更虚假？"
  },
  {
    "num": 191,
    "date": "2026-12-01",
    "title": "加载中",
    "direction": "等待加载的那几秒，是现代人最没有耐心的时刻"
  },
  {
    "num": 192,
    "date": "2026-12-02",
    "title": "404",
    "direction": "404 Not Found——有些页面消失了，就像有些人"
  }
]